<annotation>
	<folder>8</folder>
	<filename>20200219_091551_004.jpg</filename>
	<path>C:\Users\jacks\OneDrive - University of Plymouth\_Fourth Year\PRCO304\images\training\8\20200219_091551_004.jpg</path>
	<source>
		<database>Unknown</database>
	</source>
	<size>
		<width>567</width>
		<height>1008</height>
		<depth>3</depth>
	</size>
	<segmented>0</segmented>
	<object>
		<name>Pinch</name>
		<pose>Unspecified</pose>
		<truncated>0</truncated>
		<difficult>0</difficult>
		<bndbox>
			<xmin>33</xmin>
			<ymin>264</ymin>
			<xmax>102</xmax>
			<ymax>323</ymax>
		</bndbox>
	</object>
	<object>
		<name>Pinch</name>
		<pose>Unspecified</pose>
		<truncated>0</truncated>
		<difficult>0</difficult>
		<bndbox>
			<xmin>440</xmin>
			<ymin>382</ymin>
			<xmax>529</xmax>
			<ymax>448</ymax>
		</bndbox>
	</object>
	<object>
		<name>Pinch</name>
		<pose>Unspecified</pose>
		<truncated>1</truncated>
		<difficult>0</difficult>
		<bndbox>
			<xmin>512</xmin>
			<ymin>620</ymin>
			<xmax>567</xmax>
			<ymax>691</ymax>
		</bndbox>
	</object>
	<object>
		<name>Jug</name>
		<pose>Unspecified</pose>
		<truncated>0</truncated>
		<difficult>0</difficult>
		<bndbox>
			<xmin>243</xmin>
			<ymin>330</ymin>
			<xmax>343</xmax>
			<ymax>409</ymax>
		</bndbox>
	</object>
	<object>
		<name>Jug</name>
		<pose>Unspecified</pose>
		<truncated>1</truncated>
		<difficult>0</difficult>
		<bndbox>
			<xmin>466</xmin>
			<ymin>30</ymin>
			<xmax>567</xmax>
			<ymax>144</ymax>
		</bndbox>
	</object>
	<object>
		<name>Jug</name>
		<pose>Unspecified</pose>
		<truncated>0</truncated>
		<difficult>0</difficult>
		<bndbox>
			<xmin>139</xmin>
			<ymin>548</ymin>
			<xmax>209</xmax>
			<ymax>605</ymax>
		</bndbox>
	</object>
	<object>
		<name>Jug</name>
		<pose>Unspecified</pose>
		<truncated>0</truncated>
		<difficult>0</difficult>
		<bndbox>
			<xmin>87</xmin>
			<ymin>694</ymin>
			<xmax>169</xmax>
			<ymax>750</ymax>
		</bndbox>
	</object>
	<object>
		<name>Crimp</name>
		<pose>Unspecified</pose>
		<truncated>0</truncated>
		<difficult>0</difficult>
		<bndbox>
			<xmin>103</xmin>
			<ymin>461</ymin>
			<xmax>146</xmax>
			<ymax>496</ymax>
		</bndbox>
	</object>
	<object>
		<name>Pinch</name>
		<pose>Unspecified</pose>
		<truncated>0</truncated>
		<difficult>0</difficult>
		<bndbox>
			<xmin>325</xmin>
			<ymin>430</ymin>
			<xmax>358</xmax>
			<ymax>460</ymax>
		</bndbox>
	</object>
</annotation>
