<annotation>
	<folder>25</folder>
	<filename>20200219_094439_048.jpg</filename>
	<path>C:\Users\jacks\OneDrive - University of Plymouth\_Fourth Year\PRCO304\images\training\25\20200219_094439_048.jpg</path>
	<source>
		<database>Unknown</database>
	</source>
	<size>
		<width>567</width>
		<height>1008</height>
		<depth>3</depth>
	</size>
	<segmented>0</segmented>
	<object>
		<name>Jug</name>
		<pose>Unspecified</pose>
		<truncated>0</truncated>
		<difficult>0</difficult>
		<bndbox>
			<xmin>58</xmin>
			<ymin>418</ymin>
			<xmax>303</xmax>
			<ymax>595</ymax>
		</bndbox>
	</object>
	<object>
		<name>Jug</name>
		<pose>Unspecified</pose>
		<truncated>0</truncated>
		<difficult>0</difficult>
		<bndbox>
			<xmin>276</xmin>
			<ymin>549</ymin>
			<xmax>487</xmax>
			<ymax>704</ymax>
		</bndbox>
	</object>
	<object>
		<name>Hand Start</name>
		<pose>Unspecified</pose>
		<truncated>0</truncated>
		<difficult>0</difficult>
		<bndbox>
			<xmin>223</xmin>
			<ymin>593</ymin>
			<xmax>269</xmax>
			<ymax>629</ymax>
		</bndbox>
	</object>
	<object>
		<name>Hand Start</name>
		<pose>Unspecified</pose>
		<truncated>0</truncated>
		<difficult>0</difficult>
		<bndbox>
			<xmin>158</xmin>
			<ymin>812</ymin>
			<xmax>187</xmax>
			<ymax>837</ymax>
		</bndbox>
	</object>
	<object>
		<name>Sloper</name>
		<pose>Unspecified</pose>
		<truncated>0</truncated>
		<difficult>0</difficult>
		<bndbox>
			<xmin>45</xmin>
			<ymin>717</ymin>
			<xmax>168</xmax>
			<ymax>828</ymax>
		</bndbox>
	</object>
</annotation>
